smartpay/__init__.py
smartpay/payload.py
smartpay/utils.py
smartpay/version.py
smartpay/schemas/__init__.py
smartpay/schemas/flat-checkout-session-payload.jtd.json
smartpay/schemas/flat_checkout_session_payload.py
smartpay/schemas/token-checkout-session-payload.jtd.json
smartpay/schemas/token-order-payload.jtd.json
smartpay/schemas/token_checkout_session_payload.py
smartpay/schemas/token_order_payload.py
smartpay-0.8.1.dist-info/LICENSE.txt
smartpay-0.8.1.dist-info/METADATA
smartpay-0.8.1.dist-info/WHEEL
smartpay-0.8.1.dist-info/top_level.txt
smartpay-0.8.1.dist-info/RECORD
