Metadata-Version: 2.1
Name: smartpay
Version: 0.8.1
Summary: Smartpay SDK Python
Home-page: https://github.com/smartpay-co/sdk-python
Author: Smartpay Co. Ltd.
Author-email: uxe@smartpay.co
License: MIT
Classifier: License :: OSI Approved :: MIT License
Classifier: Programming Language :: Python :: 3
Classifier: Programming Language :: Python :: 3.7
License-File: LICENSE.txt
Requires-Dist: jtd (==0.1.1)
Requires-Dist: requests (==2.25.1)
